CTkTitle/CTkTitle.py
CTkTitle/__init__.py
CTk_Title_Bar-0.0.3.dist-info/LICENSE.txt
CTk_Title_Bar-0.0.3.dist-info/METADATA
CTk_Title_Bar-0.0.3.dist-info/WHEEL
CTk_Title_Bar-0.0.3.dist-info/top_level.txt
CTk_Title_Bar-0.0.3.dist-info/RECORD
