Metadata-Version: 2.1
Name: CTk-Title-Bar
Version: 0.0.3
Summary: To create customize title bar for window
Author: DKVG
Author-email: gadellidk@gmail.com
Classifier: Programming Language :: Python :: 3
Classifier: License :: OSI Approved :: MIT License
Classifier: Operating System :: OS Independent
Requires-Python: >=3.9
License-File: LICENSE.txt
